dbver/__init__.py
dbver/py.typed
dbver-0.5.1.dist-info/LICENSE
dbver-0.5.1.dist-info/METADATA
dbver-0.5.1.dist-info/WHEEL
dbver-0.5.1.dist-info/top_level.txt
dbver-0.5.1.dist-info/RECORD
