Metadata-Version: 2.1
Name: dbver
Version: 0.5.1
Summary: Unopinionated sqlite schema versioning
Home-page: https://github.com/AllSeeingEyeTolledEweSew/dbver
Author: AllSeeingEyeTolledEweSew
Author-email: asetes@pm.me
License: 0BSD
Classifier: Development Status :: 3 - Alpha
Classifier: Intended Audience :: Developers
Classifier: License :: OSI Approved :: BSD License
Classifier: Operating System :: OS Independent
Classifier: Programming Language :: Python
Classifier: Programming Language :: Python :: 3
Classifier: Programming Language :: Python :: 3 :: Only
Classifier: Programming Language :: Python :: 3.8
Classifier: Programming Language :: Python :: 3.9
Classifier: Programming Language :: Python :: 3.10
Classifier: Topic :: Database
Classifier: Topic :: Software Development :: Libraries :: Python Modules
Requires-Python: >=3.8
License-File: LICENSE
